clamnibs/__init__.py
clamnibs/base.py
clamnibs/beamformer.py
clamnibs/misc.py
clamnibs/sensor.py
clamnibs/source.py
clamnibs/stats.py
clamnibs/viz.py
clamnibs-0.1.20.dist-info/METADATA
clamnibs-0.1.20.dist-info/WHEEL
clamnibs-0.1.20.dist-info/top_level.txt
clamnibs-0.1.20.dist-info/RECORD
